pythermica/__init__.py
pythermica/analyse_nwk.py
pythermica/hdf5_process.py
pythermica/plot_variables.py
pythermica/post_process.py
pythermica/pythermica.py
pythermica-0.2.2.dist-info/AUTHORS.rst
pythermica-0.2.2.dist-info/LICENSE
pythermica-0.2.2.dist-info/METADATA
pythermica-0.2.2.dist-info/WHEEL
pythermica-0.2.2.dist-info/top_level.txt
pythermica-0.2.2.dist-info/RECORD
