Metadata-Version: 2.1
Name: pythermica
Version: 0.2.2
Summary: Post processing for Thermica simulation results
Home-page: https://github.com/astronautix/pythermica
Author: Antoine Tavant
Author-email: antoine.tavant@lpp.polytechnique.fr
License: GNU General Public License v3
Keywords: pythermica
Platform: UNKNOWN
Classifier: Development Status :: 2 - Pre-Alpha
Classifier: Intended Audience :: Developers
Classifier: License :: OSI Approved :: GNU General Public License v3 (GPLv3)
Classifier: Natural Language :: English
Classifier: Programming Language :: Python :: 3
Classifier: Programming Language :: Python :: 3.5
Classifier: Programming Language :: Python :: 3.6
Classifier: Programming Language :: Python :: 3.7
Classifier: Programming Language :: Python :: 3.8
Requires-Python: >=3.5
License-File: LICENSE
License-File: AUTHORS.rst
